Metadata-Version: 2.1
Name: roughfilter
Version: 2.0.2
Summary: With this library, you can easily catch rude expressions in text.
Home-page: https://github.com/qxtony/roughfilter
Author: qxtony
Author-email: qxtonydev@gmail.com
License: UNKNOWN
Platform: UNKNOWN
Classifier: Programming Language :: Python :: 3.10
Classifier: License :: OSI Approved :: MIT License
Classifier: Operating System :: OS Independent
Requires-Python: >=3.8
License-File: LICENSE
